pyupc_ean-2.20.10.dist-info/licenses/LICENSE
upcean/__init__.py
upcean/__main__.py
upcean/downloader.py
upcean/functions.py
upcean/support.py
upcean/svgcreate.py
upcean/versioninfo.py
upcean/convert/__init__.py
upcean/convert/convert.py
upcean/convert/shortcuts.py
upcean/decode/__init__.py
upcean/decode/barcode.py
upcean/decode/ean13.py
upcean/decode/ean8.py
upcean/decode/itf.py
upcean/decode/itf14.py
upcean/decode/shortcuts.py
upcean/decode/stf.py
upcean/decode/upca.py
upcean/decode/upce.py
upcean/decodeold/__init__.py
upcean/decodeold/barcode.py
upcean/decodeold/ean13.py
upcean/decodeold/ean8.py
upcean/decodeold/itf.py
upcean/decodeold/itf14.py
upcean/decodeold/shortcuts.py
upcean/decodeold/stf.py
upcean/decodeold/upca.py
upcean/decodeold/upce.py
upcean/encode/__init__.py
upcean/encode/barcode.py
upcean/encode/binary.py
upcean/encode/codabar.py
upcean/encode/code11.py
upcean/encode/code128.py
upcean/encode/code32.py
upcean/encode/code39.py
upcean/encode/code93.py
upcean/encode/ean13.py
upcean/encode/ean2.py
upcean/encode/ean5.py
upcean/encode/ean8.py
upcean/encode/goodwill.py
upcean/encode/itf.py
upcean/encode/itf14.py
upcean/encode/msi.py
upcean/encode/plessey.py
upcean/encode/shortcuts.py
upcean/encode/stf.py
upcean/encode/upca.py
upcean/encode/upcavar.py
upcean/encode/upce.py
upcean/fonts/OCRA.otf
upcean/fonts/OCRA.ttf
upcean/fonts/OCRB.otf
upcean/fonts/OCRB.ttf
upcean/fonts/OCRBE.otf
upcean/fonts/OCRBE.ttf
upcean/fonts/OCRBF.otf
upcean/fonts/OCRBF.ttf
upcean/fonts/OCRBL.otf
upcean/fonts/OCRBL.ttf
upcean/fonts/OCRBS.otf
upcean/fonts/OCRBS.ttf
upcean/fonts/OCRBX.otf
upcean/fonts/OCRBX.ttf
upcean/fonts/__init__.py
upcean/getprefix/__init__.py
upcean/getprefix/countries.py
upcean/getprefix/getprefix.py
upcean/getprefix/shortcuts.py
upcean/oopfuncs/__init__.py
upcean/oopfuncs/oopfuncs.py
upcean/oopfuncs/shortcuts.py
upcean/predraw/__init__.py
upcean/predraw/gdlib.py
upcean/predraw/getsfname.py
upcean/predraw/precairo.py
upcean/predraw/precv2.py
upcean/predraw/predrawlib.py
upcean/predraw/prefuncs.py
pyupc_ean-2.20.10.dist-info/METADATA
pyupc_ean-2.20.10.dist-info/WHEEL
pyupc_ean-2.20.10.dist-info/top_level.txt
pyupc_ean-2.20.10.dist-info/RECORD
