Metadata-Version: 2.4
Name: PyUPC-EAN
Version: 2.20.10
Summary: A barcode library/module for python.
Home-page: https://github.com/GameMaker2k/PyUPC-EAN
Download-URL: https://github.com/GameMaker2k/PyUPC-EAN/archive/master.tar.gz
Author: Kazuki Przyborowski
Author-email: Kazuki Przyborowski <kazuki.przyborowski@gmail.com>
Maintainer: Kazuki Przyborowski
Maintainer-email: kazuki.przyborowski@gmail.com
License: BSD-3-Clause
Platform: OS Independent
License-File: LICENSE
Dynamic: author
Dynamic: download-url
Dynamic: home-page
Dynamic: license-file
Dynamic: maintainer
Dynamic: maintainer-email
Dynamic: platform
